Metadata-Version: 2.1
Name: drf-yasg-edge
Version: 2.1
Summary: Automated generation of real Swagger/OpenAPI 2.0 schemas from Django Rest Framework code.
Home-page: https://github.com/banxi1988/drf-yasg
Author: Cristi V.
Author-email: cristi@cvjd.me, banxi1988@gmail.com
License: BSD License
Keywords: drf django django-rest-framework schema swagger openapi codegen swagger-codegen documentation drf-yasg django-rest-swagger drf-openapi
Platform: UNKNOWN
Classifier: Intended Audience :: Developers
Classifier: License :: OSI Approved :: BSD License
Classifier: Development Status :: 5 - Production/Stable
Classifier: Operating System :: OS Independent
Classifier: Environment :: Web Environment
Classifier: Framework :: Django
Classifier: Framework :: Django :: 2.2
Classifier: Framework :: Django :: 3.0
Classifier: Topic :: Documentation
Classifier: Topic :: Software Development :: Code Generators
Classifier: Programming Language :: Python
Classifier: Programming Language :: Python :: 3
Classifier: Programming Language :: Python :: 3.7
Classifier: Programming Language :: Python :: 3.8
Requires-Python: >=3.6
Requires-Dist: coreapi (>=2.3.3)
Requires-Dist: coreschema (>=0.0.4)
Requires-Dist: ruamel.yaml (>=0.15.34)
Requires-Dist: inflection (>=0.3.1)
Requires-Dist: uritemplate (>=3.0.0)
Requires-Dist: packaging
Requires-Dist: djangorestframework (>=3.10)
Requires-Dist: Django (>=2.2.0)
Requires-Dist: typing-extensions (>=3.7.4)
Provides-Extra: validation
Requires-Dist: swagger-spec-validator (>=2.1.0) ; extra == 'validation'
